{
  "meta.pack_name": "MineIt Narrative Strings (EN)",
  "meta.pack_version": "1.0",
  "meta.notes": "Developer-facing narrative text pack aligned to MineIt v3.2 gameplay loop and UI. Uses string.Format placeholders {0}..{n}.",

  "world.town_name": "Cairn",
  "world.planet_name": "Vesper",
  "world.registry_name": "Cairn Registry",
  "world.vault_name": "Town Vault",
  "world.hush_name": "the hush",
  "world.directive_name": "Recovery Directive",

  "ui.common.ok": "OK",
  "ui.common.cancel": "Cancel",
  "ui.common.close": "Close",
  "ui.common.back": "Back",
  "ui.common.continue": "Continue",
  "ui.common.confirm": "Confirm",
  "ui.common.yes": "Yes",
  "ui.common.no": "No",
  "ui.common.enabled": "Enabled",
  "ui.common.disabled": "Disabled",
  "ui.common.unknown": "Unknown",
  "ui.common.none": "None",
  "ui.common.new": "New",
  "ui.common.locked": "Locked",
  "ui.common.warning": "Warning",
  "ui.common.urgent": "Urgent",
  "ui.common.tip": "Tip",

  "ui.units.credits": "cr",
  "ui.units.kg": "kg",
  "ui.units.tiles": "tiles",
  "ui.units.meters": "m",
  "ui.units.seconds": "s",
  "ui.units.days": "days",

  "ui.format.credits": "{0} cr",
  "ui.format.kg": "{0} kg",
  "ui.format.tiles": "{0} tiles",
  "ui.format.meters": "{0} m",
  "ui.format.seconds": "{0} s",
  "ui.format.percent": "{0}%",

  "ui.region.band0.name": "Town Safe Zone",
  "ui.region.band0.subtitle": "The Lit Perimeter",
  "ui.region.band1.name": "Foothills",
  "ui.region.band1.subtitle": "The First Quiet",
  "ui.region.band2.name": "Highlands",
  "ui.region.band2.subtitle": "The Mineral Spine",
  "ui.region.band3.name": "Alpine",
  "ui.region.band3.subtitle": "The Knife Country",
  "ui.region.band4.name": "Badlands",
  "ui.region.band4.subtitle": "The Anomaly Belt",

  "ui.hud.header.day": "Day {0}",
  "ui.hud.header.time": "{0}:{1}",
  "ui.hud.header.location": "{0} — {1}",
  "ui.hud.header.location_simple": "{0}",

  "ui.hud.credits.label": "Credits",
  "ui.hud.credits.value": "{0} cr",
  "ui.hud.backpack.label": "Backpack",
  "ui.hud.backpack.value": "{0}/{1} kg",
  "ui.hud.backpack.value_over": "{0}/{1} kg (Overloaded)",
  "ui.hud.backpack.empty": "Backpack empty",
  "ui.hud.backpack.full": "Backpack full",
  "ui.hud.storage.label": "Town Storage",
  "ui.hud.storage.hint": "Deposit in town to sell",

  "ui.hud.tooltip.hush": "Interference is heavy here. Map certainty must be earned.",
  "ui.hud.tooltip.fog_undiscovered": "Undiscovered: no reliable survey record.",
  "ui.hud.tooltip.fog_discovered": "Discovered: recorded survey signature; not currently in view.",
  "ui.hud.tooltip.fog_visible": "Visible: live resolution from active sensors.",

  "ui.hud.scan.button": "Scan",
  "ui.hud.scan.button_alt": "Emit Pulse",
  "ui.hud.scan.button_disabled_cooldown": "Scan (Cooling)",
  "ui.hud.scan.cooldown": "Cooldown: {0}s",
  "ui.hud.scan.cooldown_tooltip": "Coils recovering. Another pulse now would be noise.",
  "ui.hud.scan.broadcast_hint": "Pulse afterglow may be detectable by rivals.",
  "ui.hud.scan.broadcast_hint_strong": "Broadcast risk: rivals can triangulate the afterglow.",
  "ui.hud.scan.result_panel.title": "Scan Intelligence",
  "ui.hud.scan.result_panel.subtitle": "Ranked by value density, estimated size, and distance.",
  "ui.hud.scan.result_panel.empty": "No viable echoes in range.",
  "ui.hud.scan.result_panel.empty_tip": "Move, then scan again. The ground does not speak twice from the same angle.",
  "ui.hud.scan.results.header.rank": "#",
  "ui.hud.scan.results.header.ore": "Ore",
  "ui.hud.scan.results.header.depth": "Depth",
  "ui.hud.scan.results.header.distance": "Distance",
  "ui.hud.scan.results.header.size": "Est. Size",
  "ui.hud.scan.results.header.tags": "Tags",
  "ui.hud.scan.results.header.eta": "ETA",

  "ui.hud.scan.tag.npc": "NPC",
  "ui.hud.scan.tag.deep": "Deep",
  "ui.hud.scan.tag.urgent": "Urgent",
  "ui.hud.scan.tag.warning": "Warning",
  "ui.hud.scan.tag.depleted": "Depleted",
  "ui.hud.scan.tag.claimed_player": "Yours",
  "ui.hud.scan.tag.claimed_none": "Unclaimed",

  "ui.hud.scan.tag_tooltip.npc": "Registry shows a rival beacon on this site.",
  "ui.hud.scan.tag_tooltip.deep": "Detected depth exceeds current cutter capability. Mark for later.",
  "ui.hud.scan.tag_tooltip.urgent": "Depletion trend indicates imminent exhaustion. Decide now.",
  "ui.hud.scan.tag_tooltip.warning": "Depletion trending fast. You have a narrow window.",
  "ui.hud.scan.tag_tooltip.depleted": "Archived site. No extractable material remains.",
  "ui.hud.scan.tag_tooltip.yours": "Claim verified. Exclusive extraction rights active.",

  "ui.hud.scan.size_estimate": "Tier {0} (±{1})",
  "ui.hud.scan.size_estimate_exact": "Tier {0}",

  "ui.hud.extraction.title": "Extraction",
  "ui.hud.extraction.rate": "Rate: {0} kg/s",
  "ui.hud.extraction.rate_with_difficulty": "Rate: {0} kg/s (adjusted)",
  "ui.hud.extraction.eta": "ETA: {0}s",
  "ui.hud.extraction.eta_unknown": "ETA: Unknown",
  "ui.hud.extraction.prompt_start": "Hold to extract",
  "ui.hud.extraction.prompt_stop": "Release to stop",
  "ui.hud.extraction.status_active": "Extracting…",
  "ui.hud.extraction.status_idle": "Idle",
  "ui.hud.extraction.status_blocked": "Blocked",
  "ui.hud.extraction.blocked_out_of_range": "Out of range. Reposition and re-engage.",
  "ui.hud.extraction.blocked_backpack_full": "Backpack full. Return to town or deposit to storage.",
  "ui.hud.extraction.blocked_not_claimed": "Unclaimed site. Claim required.",
  "ui.hud.extraction.blocked_claimed_by_npc": "Registry lockout: rival claim detected.",
  "ui.hud.extraction.blocked_claimed_by_player_other": "Registry lockout: claim mismatch.",
  "ui.hud.extraction.blocked_depleted": "Site depleted. No extractable material remains.",
  "ui.hud.extraction.blocked_too_deep": "Cutter depth insufficient. Upgrade extractor to proceed.",

  "ui.hud.claim.title": "Claim",
  "ui.hud.claim.prompt": "Hold to claim",
  "ui.hud.claim.channeling": "Claim Packet Uploading…",
  "ui.hud.claim.channeling_seconds": "Claiming… {0:0.0}s",
  "ui.hud.claim.complete": "Claim verified.",
  "ui.hud.claim.failed": "Claim failed.",
  "ui.hud.claim.failed_out_of_range": "Handshake broken: moved out of claim range.",
  "ui.hud.claim.failed_already_claimed": "Claim denied: site already claimed.",
  "ui.hud.claim.failed_not_discovered": "Claim denied: no survey record. Scan required.",
  "ui.hud.claim.failed_depleted": "Claim denied: archived site.",

  "ui.hud.waypoint.title": "Waypoint",
  "ui.hud.waypoint.set": "Waypoint set.",
  "ui.hud.waypoint.cleared": "Waypoint cleared.",
  "ui.hud.waypoint.distance": "Distance: {0} tiles",
  "ui.hud.waypoint.none": "No waypoint",
  "ui.hud.waypoint.auto_set_on_scan": "Auto-waypoint: highest priority echo selected.",
  "ui.hud.waypoint.compass_hint": "Follow the compass arrow to your waypoint.",

  "ui.map.title": "Map",
  "ui.map.hint.open": "Press M to open map",
  "ui.map.hint.close": "Press M to close map",
  "ui.map.legend.title": "Legend",
  "ui.map.legend.player": "You",
  "ui.map.legend.town": "{0}",
  "ui.map.legend.deposit_unclaimed": "Deposit (Unclaimed)",
  "ui.map.legend.deposit_player": "Deposit (Yours)",
  "ui.map.legend.deposit_npc": "Deposit (NPC)",
  "ui.map.legend.deposit_depleted": "Deposit (Depleted)",
  "ui.map.legend.waypoint": "Waypoint",
  "ui.map.action.set_waypoint": "Set Waypoint",
  "ui.map.action.clear_waypoint": "Clear Waypoint",
  "ui.map.action.fast_travel": "Fast Travel",
  "ui.map.action.fast_travel_to_town": "Fast Travel to {0}",
  "ui.map.action.fast_travel_tooltip": "Recall tether service. Costs scale with distance.",
  "ui.map.tooltip.deposit": "{0} deposit\nDepth: {1} m\nStatus: {2}",
  "ui.map.tooltip.deposit_depleted": "{0} deposit (Depleted)\nRegistry record archived.",
  "ui.map.tooltip.deposit_claimed_player": "{0} deposit (Yours)\nExclusive rights active.",
  "ui.map.tooltip.deposit_claimed_npc": "{0} deposit (NPC)\nRival beacon detected.",
  "ui.map.tooltip.waypoint": "Waypoint\nDistance: {0} tiles",
  "ui.map.tooltip.town": "{0}\nSafe zone boundary nearby.",

  "ui.fasttravel.title": "Fast Travel",
  "ui.fasttravel.request": "Request Recall Tether",
  "ui.fasttravel.cost": "Cost: {0} cr",
  "ui.fasttravel.cost_detail": "Recall burn fee (distance-based).",
  "ui.fasttravel.confirm": "Fast travel to {0} for {1} cr?",
  "ui.fasttravel.confirm_subtitle": "Waypoint will remain unchanged.",
  "ui.fasttravel.blocked_insufficient_credits": "Recall denied: insufficient credits.",
  "ui.fasttravel.blocked_already_in_town": "You are already in town range.",
  "ui.fasttravel.success": "Recall tether engaged.",
  "ui.fasttravel.arrived": "Arrived at {0}.",

  "ui.town.title": "{0}",
  "ui.town.subtitle": "Registry • Market • Vault",
  "ui.town.panel.deposit.title": "Deposit",
  "ui.town.panel.deposit.button": "Deposit Backpack",
  "ui.town.panel.deposit.tooltip": "Transfer contents to bonded storage for sale or vault intake.",
  "ui.town.panel.deposit.empty": "Nothing to deposit.",
  "ui.town.panel.deposit.success": "Backpack deposited to storage.",
  "ui.town.panel.deposit.moved_stacks": "Transferred {0} stack(s) to storage.",
  "ui.town.panel.sell.title": "Sell",
  "ui.town.panel.sell.button": "Sell Storage",
  "ui.town.panel.sell.tooltip": "Liquidate sellable storage contents at Registry rates.",
  "ui.town.panel.sell.empty": "No sellable material in storage.",
  "ui.town.panel.sell.success": "Sale complete: +{0} cr",
  "ui.town.panel.sell.detail": "Sold {0} stack(s).",
  "ui.town.panel.sell.preview.title": "Sale Preview",
  "ui.town.panel.sell.preview.empty": "Nothing sellable detected.",
  "ui.town.panel.sell.preview.total": "Total: {0} cr",
  "ui.town.panel.sell.preview.line": "{0} × {1} = {2} cr",

  "ui.town.panel.upgrades.title": "Upgrades",
  "ui.town.panel.upgrades.subtitle": "Authorize retrofits • Licensed components",
  "ui.town.panel.upgrade.detector": "Detector",
  "ui.town.panel.upgrade.extractor": "Extractor",
  "ui.town.panel.upgrade.backpack": "Backpack",
  "ui.town.panel.upgrade.current_tier": "Current Tier: {0}",
  "ui.town.panel.upgrade.next_tier": "Next Tier: {0}",
  "ui.town.panel.upgrade.maxed": "Max Tier reached.",
  "ui.town.panel.upgrade.buy_next": "Buy Next Tier",
  "ui.town.panel.upgrade.cost": "Cost: {0} cr",
  "ui.town.panel.upgrade.cost_insufficient": "Cost: {0} cr (Insufficient)",
  "ui.town.panel.upgrade.confirm": "Authorize {0} upgrade to Tier {1} for {2} cr?",
  "ui.town.panel.upgrade.confirm_subtitle": "Retrofit is immediate. Registry will log the change.",
  "ui.town.panel.upgrade.success": "{0} upgraded to Tier {1}.",
  "ui.town.panel.upgrade.failed": "Upgrade failed.",
  "ui.town.panel.upgrade.failed_insufficient_credits": "Upgrade denied: insufficient credits.",
  "ui.town.panel.upgrade.failed_max_tier": "Upgrade denied: already at max tier.",
  "ui.town.panel.upgrade.failed_unknown": "Upgrade denied: authorization error.",

  "ui.town.panel.stats.title": "Rig Status",
  "ui.town.panel.stats.credits": "Credits: {0} cr",
  "ui.town.panel.stats.detector": "Detector Tier: {0}",
  "ui.town.panel.stats.extractor": "Extractor Tier: {0}",
  "ui.town.panel.stats.backpack": "Backpack Tier: {0}",
  "ui.town.panel.stats.detector_detail": "Scan Radius: {0} tiles • Max Depth: {1} m • Cooldown: {2}s",
  "ui.town.panel.stats.extractor_detail": "Base Rate: {0} kg/s • Max Depth: {1} m",
  "ui.town.panel.stats.backpack_detail": "Capacity: {0} kg",

  "ui.notifications.scan.pulse_emitted": "Pulse emitted. Echoes resolving…",
  "ui.notifications.scan.no_results": "No viable echoes detected.",
  "ui.notifications.scan.results_found": "Scan complete: {0} site(s) detected.",
  "ui.notifications.scan.contested_window": "Afterglow active — rivals may respond for {0}s.",
  "ui.notifications.scan.contested_window_short": "Broadcast risk: {0}s.",
  "ui.notifications.scan.auto_waypoint_set": "Auto-waypoint set to highest priority echo.",
  "ui.notifications.scan.deposit_marked": "Site marked on map.",
  "ui.notifications.scan.deep_detected": "Deep signature detected. Upgrade required to extract.",

  "ui.notifications.claim.started": "Claim channel opened.",
  "ui.notifications.claim.completed": "Claim verified: exclusive rights active.",
  "ui.notifications.claim.cancelled": "Claim cancelled.",
  "ui.notifications.claim.denied_already_claimed": "Claim denied: rival beacon present.",
  "ui.notifications.claim.denied_not_discovered": "Claim denied: scan required.",
  "ui.notifications.claim.denied_depleted": "Claim denied: archived site.",

  "ui.notifications.extract.start": "Extraction engaged.",
  "ui.notifications.extract.stop": "Extraction halted.",
  "ui.notifications.extract.backpack_full": "Backpack full. Return to town.",
  "ui.notifications.extract.depleted": "Site depleted. Registry record archived.",
  "ui.notifications.extract.lockout_npc": "Extraction lockout: rival claim detected.",
  "ui.notifications.extract.too_deep": "Depth beyond current cutter. Upgrade extractor.",

  "ui.notifications.npc.claimed": "Registry update: rival claim detected on a scanned site.",
  "ui.notifications.npc.depletion_warning": "Rival extraction trending fast — depletion likely within {0}s.",
  "ui.notifications.npc.depletion_urgent": "Urgent: rival site may deplete within {0}s.",

  "ui.notifications.waypoint.set": "Waypoint set.",
  "ui.notifications.waypoint.cleared": "Waypoint cleared.",
  "ui.notifications.fasttravel.denied": "Recall denied: insufficient credits.",
  "ui.notifications.fasttravel.engaged": "Recall tether engaged.",
  "ui.notifications.fasttravel.arrived": "Recall complete.",

  "ui.notifications.save.saving": "Saving…",
  "ui.notifications.save.saved": "Saved.",
  "ui.notifications.save.failed": "Save failed.",
  "ui.notifications.load.loading": "Loading…",
  "ui.notifications.load.loaded": "Loaded.",
  "ui.notifications.load.failed": "Load failed.",

  "ui.artifacts.title": "Artifacts",
  "ui.artifacts.subtitle": "Quarantine-class recoveries • Vault intake required",
  "ui.artifacts.tracker": "Secured: {0}/6",
  "ui.artifacts.tracker_line": "{0}: {1}",
  "ui.artifacts.status.missing": "Missing",
  "ui.artifacts.status.secured": "Secured",
  "ui.artifacts.status.in_backpack": "In Backpack",
  "ui.artifacts.status.in_storage": "In Storage",
  "ui.artifacts.status.unknown": "Unknown",

  "ui.artifacts.requirements.title": "Requirements",
  "ui.artifacts.requirements.detector": "Detector Tier 5 required for reliable identification.",
  "ui.artifacts.requirements.extractor": "Extractor Tier 5 required for safe extraction.",
  "ui.artifacts.requirements.band4": "Artifact-class signatures occur only in the Badlands.",
  "ui.artifacts.requirements.vault": "Victory requires all artifacts deposited in Town Storage.",

  "ui.artifacts.discovery.header": "Anomalous Deposit Detected",
  "ui.artifacts.discovery.body": "Signature does not match known ore. Quarantine protocol recommended.",
  "ui.artifacts.discovery.body_strong": "Quarantine-class signature confirmed. Vault intake required.",
  "ui.artifacts.discovery.tip": "Claim quickly. Rivals cannot extract artifact-class sites, but they can drain nearby ore and force hard choices.",
  "ui.artifacts.extraction.locked_detector": "Identification unreliable. Upgrade Detector to Tier 5.",
  "ui.artifacts.extraction.locked_extractor": "Extraction unsafe. Upgrade Extractor to Tier 5.",
  "ui.artifacts.extraction.allowed": "Containment handshake active. Proceed with caution.",
  "ui.artifacts.deposit.prompt": "Deposit artifact to storage for Vault intake.",
  "ui.artifacts.deposit.success": "Artifact secured in storage. Vault authentication queued.",
  "ui.artifacts.deposit.denied_not_in_town": "Vault intake unavailable outside town.",
  "ui.artifacts.deposit.denied_not_in_storage": "Artifact must be in storage to authenticate.",
  "ui.artifacts.vault.intake_started": "Vault intake engaged. Do not remove item.",
  "ui.artifacts.vault.intake_complete": "Vault authentication complete.",

  "artifact.stellar_shard.name": "Stellar Shard",
  "artifact.stellar_shard.short": "Black-glass metal that reflects starlight underground.",
  "artifact.stellar_shard.discovery": "The echo arrives before the pulse finishes. Your HUD rejects the timing, then accepts it anyway.",
  "artifact.stellar_shard.tooltip": "Quarantine-Class Object: Resonance return exhibits non-causal phase behavior. Store in the Vault’s null-light compartment.",

  "artifact.ancient_lattice.name": "Ancient Lattice",
  "artifact.ancient_lattice.short": "A folded grid of metallic filaments, impossibly thin.",
  "artifact.ancient_lattice.discovery": "Your detector reports multiple sizes at once. The hush stops sounding like noise and starts sounding like a warning.",
  "artifact.ancient_lattice.tooltip": "Quarantine-Class Object: Field-sensitive framework. Vault storage requires a containment cage to prevent unfolding.",

  "artifact.void_compass.name": "Void Compass",
  "artifact.void_compass.short": "A ringed mechanism that orients to a direction your maps cannot name.",
  "artifact.void_compass.discovery": "It settles with certainty. The compass arrow in your HUD feels suddenly… embarrassed.",
  "artifact.void_compass.tooltip": "Quarantine-Class Object: Orientation anchor unknown. Registry mandates immediate Vault intake. Do not attempt calibration.",

  "artifact.quantum_fossil.name": "Quantum Fossil",
  "artifact.quantum_fossil.short": "Stone that holds motion—patterns shifting when you look away.",
  "artifact.quantum_fossil.discovery": "The deposit reads like geology until Tier 5 resolves the coherence inside it. The ground is not merely old; it is edited.",
  "artifact.quantum_fossil.tooltip": "Quarantine-Class Object: Phase-unstable internal structure. Vault stores in thermal stabilizer to reduce drift.",

  "artifact.machine_relic.name": "Machine Relic",
  "artifact.machine_relic.short": "A scorched actuator core with joints that twitch under scan.",
  "artifact.machine_relic.discovery": "Your extractor vibrates against something that should not respond. It does. Slowly. Like it’s waking up.",
  "artifact.machine_relic.tooltip": "Quarantine-Class Object: Reactivity risk. Vault seal required to prevent unauthorized activation.",

  "artifact.echo_prism.name": "Echo Prism",
  "artifact.echo_prism.short": "A crystalline prism that refracts sound and light into shapes.",
  "artifact.echo_prism.discovery": "The scan returns twice—once for where it is, once for where it wants to be. The hush goes quiet, as if listening.",
  "artifact.echo_prism.tooltip": "Quarantine-Class Object: Signal-active medium. Vault stores in shielded node to prevent echo bleed into Registry bands.",

  "ui.victory.title": "DIRECTIVE COMPLETE",
  "ui.victory.subtitle": "Artifacts secured in the Vault.",
  "ui.victory.seed": "Seed: {0}",
  "ui.victory.time": "Completion Time: {0} days {1}:{2}",
  "ui.victory.registry": "{0}: Record archived.",
  "ui.victory.button_continue": "Continue Sandbox",
  "ui.victory.button_main_menu": "Main Menu",
  "ui.victory.flavor_1": "Cairn goes quiet when the Vault door seals.",
  "ui.victory.flavor_2": "The ground kept its secrets. You brought back the proof.",
  "ui.victory.flavor_3": "The Registry prints your time like a verdict.",

  "ui.save.title": "Save/Load",
  "ui.save.slot": "Slot {0}",
  "ui.save.timestamp": "Last Played: {0}",
  "ui.save.seed": "Seed: {0}",
  "ui.save.version": "Save Version: {0}",
  "ui.save.content_version": "Content: {0}",
  "ui.save.new_game": "New Game",
  "ui.save.load_game": "Load Game",
  "ui.save.delete_game": "Delete Save",
  "ui.save.confirm_delete": "Delete this save? This cannot be undone.",
  "ui.save.migrating": "Migrating save data…",
  "ui.save.migration_complete": "Migration complete.",
  "ui.save.migration_failed": "Migration failed. Save may be incompatible.",

  "ui.errors.generic": "Action failed.",
  "ui.errors.not_in_town": "Unavailable outside town.",
  "ui.errors.insufficient_credits": "Insufficient credits.",
  "ui.errors.inventory_full": "Backpack full.",
  "ui.errors.storage_empty": "Storage empty.",
  "ui.errors.sell_nothing": "Nothing sellable.",
  "ui.errors.upgrade_max_tier": "Max tier reached.",
  "ui.errors.upgrade_requires_previous": "Previous tier required.",
  "ui.errors.deposit_not_discovered": "No survey record. Scan required.",
  "ui.errors.deposit_already_claimed": "Site already claimed.",
  "ui.errors.deposit_claimed_by_npc": "Rival claim detected. Extraction locked.",
  "ui.errors.deposit_claimed_by_player": "Already claimed by you.",
  "ui.errors.deposit_depleted": "Site depleted.",
  "ui.errors.deposit_out_of_range": "Out of range.",
  "ui.errors.deposit_too_deep": "Too deep for current equipment.",
  "ui.errors.scan_on_cooldown": "Scan coils are cooling.",
  "ui.errors.fasttravel_cost_too_high": "Recall fee exceeds allowed maximum.",
  "ui.errors.save_failed_io": "Save failed: storage unavailable.",
  "ui.errors.load_failed_corrupt": "Load failed: save data corrupt or incomplete.",

  "ore.scrap.name": "Scrap",
  "ore.scrap.short": "Shattered alloys and salvage-grade composites.",
  "ore.copper.name": "Copper",
  "ore.copper.short": "Conductive seam metal used in coils and power systems.",
  "ore.iron.name": "Iron",
  "ore.iron.short": "Structural ore; heavy, reliable, and always in demand.",
  "ore.quartz.name": "Quartz",
  "ore.quartz.short": "Crystalline material used in photonics and precision resonators.",
  "ore.lithium.name": "Lithium",
  "ore.lithium.short": "Reactive energy-storage mineral; valuable and light.",
  "ore.titanium.name": "Titanium",
  "ore.titanium.short": "High-strength metal; hard work, high reward.",
  "ore.cobalt.name": "Cobalt",
  "ore.cobalt.short": "Dense deep ore used in high-performance alloys.",
  "ore.neodymium.name": "Neodymium",
  "ore.neodymium.short": "Rare earth seam with strong field behavior.",
  "ore.xenonite.name": "Xenonite",
  "ore.xenonite.short": "Exotic hybrid crystal-metal with anomalous resonance.",

  "lore.tip.scan_tradeoff": "Every scan buys knowledge. It also buys attention.",
  "lore.tip.claim_fast": "If you want it, claim it. The Registry favors whoever signs first.",
  "lore.tip.depleted_markers": "Depleted sites are not mistakes. They’re proof.",
  "lore.tip.badlands": "In the Badlands, the hush stops acting like interference and starts acting like intent.",

  "lore.toast.night_1": "Night falls. Your lamp bubble feels smaller than it should.",
  "lore.toast.night_2": "The hush thickens in the dark. Your map remembers what you earn.",
  "lore.toast.day_1": "Morning light. Same ground. New echoes.",
  "lore.toast.day_2": "Day cycle resets. Rival crews don’t sleep—only their machines do.",

  "lore.registry.flavor_1": "Registry Notice: claim packets are audited. Fraud is exile.",
  "lore.registry.flavor_2": "Registry Notice: quarantine-class salvage must be deposited immediately.",
  "lore.vault.flavor_1": "Vault Intake: containment handshake confirmed.",
  "lore.vault.flavor_2": "Vault Intake: authentication queued. Do not interfere.",

  "ui.debug.deposit_id": "Deposit ID: {0}",
  "ui.debug.seed": "Seed: {0}",
  "ui.debug.clock": "Clock: Day {0} {1}:{2}",
  "ui.debug.region_band": "Region Band: {0}"
}
